{
    "Meta Data":  {
                      "1. Information":  "Daily Prices (open, high, low, close) and Volumes",
                      "2. Symbol":  "XXI",
                      "3. Last Refreshed":  "2026-06-22",
                      "4. Output Size":  "Compact",
                      "5. Time Zone":  "US/Eastern"
                  },
    "Time Series (Daily)":  {
                                "2026-06-22":  {
                                                   "1. open":  "5.6700",
                                                   "2. high":  "6.0029",
                                                   "3. low":  "5.6600",
                                                   "4. close":  "5.7400",
                                                   "5. volume":  "1492640"
                                               },
                                "2026-06-18":  {
                                                   "1. open":  "5.6800",
                                                   "2. high":  "5.6900",
                                                   "3. low":  "5.3100",
                                                   "4. close":  "5.5200",
                                                   "5. volume":  "2862321"
                                               },
                                "2026-06-17":  {
                                                   "1. open":  "5.9600",
                                                   "2. high":  "6.0700",
                                                   "3. low":  "5.6400",
                                                   "4. close":  "5.6400",
                                                   "5. volume":  "1217872"
                                               },
                                "2026-06-16":  {
                                                   "1. open":  "6.0500",
                                                   "2. high":  "6.1650",
                                                   "3. low":  "5.9800",
                                                   "4. close":  "6.0000",
                                                   "5. volume":  "1136001"
                                               },
                                "2026-06-15":  {
                                                   "1. open":  "6.0000",
                                                   "2. high":  "6.2899",
                                                   "3. low":  "5.9600",
                                                   "4. close":  "6.0800",
                                                   "5. volume":  "1172724"
                                               },
                                "2026-06-12":  {
                                                   "1. open":  "5.7000",
                                                   "2. high":  "6.0150",
                                                   "3. low":  "5.6900",
                                                   "4. close":  "5.7700",
                                                   "5. volume":  "1132900"
                                               },
                                "2026-06-11":  {
                                                   "1. open":  "5.4000",
                                                   "2. high":  "5.7900",
                                                   "3. low":  "5.3100",
                                                   "4. close":  "5.7200",
                                                   "5. volume":  "1603391"
                                               },
                                "2026-06-10":  {
                                                   "1. open":  "5.4200",
                                                   "2. high":  "5.5100",
                                                   "3. low":  "5.3200",
                                                   "4. close":  "5.3400",
                                                   "5. volume":  "987496"
                                               },
                                "2026-06-09":  {
                                                   "1. open":  "5.8100",
                                                   "2. high":  "5.8700",
                                                   "3. low":  "5.4800",
                                                   "4. close":  "5.5000",
                                                   "5. volume":  "1145232"
                                               },
                                "2026-06-08":  {
                                                   "1. open":  "5.9000",
                                                   "2. high":  "5.9400",
                                                   "3. low":  "5.7200",
                                                   "4. close":  "5.8400",
                                                   "5. volume":  "1047447"
                                               },
                                "2026-06-05":  {
                                                   "1. open":  "6.1200",
                                                   "2. high":  "6.1200",
                                                   "3. low":  "5.5150",
                                                   "4. close":  "5.6400",
                                                   "5. volume":  "2353150"
                                               },
                                "2026-06-04":  {
                                                   "1. open":  "6.2300",
                                                   "2. high":  "6.4000",
                                                   "3. low":  "6.2100",
                                                   "4. close":  "6.2600",
                                                   "5. volume":  "2044324"
                                               },
                                "2026-06-03":  {
                                                   "1. open":  "6.5200",
                                                   "2. high":  "6.6000",
                                                   "3. low":  "6.3700",
                                                   "4. close":  "6.4200",
                                                   "5. volume":  "1676676"
                                               },
                                "2026-06-02":  {
                                                   "1. open":  "7.0200",
                                                   "2. high":  "7.0400",
                                                   "3. low":  "6.4100",
                                                   "4. close":  "6.6700",
                                                   "5. volume":  "2558209"
                                               },
                                "2026-06-01":  {
                                                   "1. open":  "7.1000",
                                                   "2. high":  "7.2150",
                                                   "3. low":  "6.8100",
                                                   "4. close":  "7.1700",
                                                   "5. volume":  "1765901"
                                               },
                                "2026-05-29":  {
                                                   "1. open":  "7.2500",
                                                   "2. high":  "7.6150",
                                                   "3. low":  "7.1501",
                                                   "4. close":  "7.3200",
                                                   "5. volume":  "1259493"
                                               },
                                "2026-05-28":  {
                                                   "1. open":  "7.1400",
                                                   "2. high":  "7.3700",
                                                   "3. low":  "7.0300",
                                                   "4. close":  "7.3300",
                                                   "5. volume":  "1006107"
                                               },
                                "2026-05-27":  {
                                                   "1. open":  "7.1000",
                                                   "2. high":  "7.3650",
                                                   "3. low":  "7.0700",
                                                   "4. close":  "7.3300",
                                                   "5. volume":  "1055902"
                                               },
                                "2026-05-26":  {
                                                   "1. open":  "7.3200",
                                                   "2. high":  "7.5400",
                                                   "3. low":  "7.0850",
                                                   "4. close":  "7.1700",
                                                   "5. volume":  "1408905"
                                               },
                                "2026-05-22":  {
                                                   "1. open":  "7.6400",
                                                   "2. high":  "7.6800",
                                                   "3. low":  "7.2900",
                                                   "4. close":  "7.3200",
                                                   "5. volume":  "1649924"
                                               },
                                "2026-05-21":  {
                                                   "1. open":  "7.7500",
                                                   "2. high":  "7.8566",
                                                   "3. low":  "7.5100",
                                                   "4. close":  "7.6400",
                                                   "5. volume":  "1135158"
                                               },
                                "2026-05-20":  {
                                                   "1. open":  "7.8500",
                                                   "2. high":  "7.9950",
                                                   "3. low":  "7.6600",
                                                   "4. close":  "7.7900",
                                                   "5. volume":  "1030683"
                                               },
                                "2026-05-19":  {
                                                   "1. open":  "7.7400",
                                                   "2. high":  "7.8500",
                                                   "3. low":  "7.6100",
                                                   "4. close":  "7.6200",
                                                   "5. volume":  "840096"
                                               },
                                "2026-05-18":  {
                                                   "1. open":  "7.7500",
                                                   "2. high":  "7.9850",
                                                   "3. low":  "7.6598",
                                                   "4. close":  "7.7700",
                                                   "5. volume":  "1085876"
                                               },
                                "2026-05-15":  {
                                                   "1. open":  "8.1500",
                                                   "2. high":  "8.1899",
                                                   "3. low":  "7.7501",
                                                   "4. close":  "7.9100",
                                                   "5. volume":  "969345"
                                               },
                                "2026-05-14":  {
                                                   "1. open":  "8.0300",
                                                   "2. high":  "8.5700",
                                                   "3. low":  "7.9700",
                                                   "4. close":  "8.3900",
                                                   "5. volume":  "1399836"
                                               },
                                "2026-05-13":  {
                                                   "1. open":  "8.3500",
                                                   "2. high":  "8.3500",
                                                   "3. low":  "7.9500",
                                                   "4. close":  "7.9600",
                                                   "5. volume":  "962690"
                                               },
                                "2026-05-12":  {
                                                   "1. open":  "8.5200",
                                                   "2. high":  "8.5400",
                                                   "3. low":  "8.1650",
                                                   "4. close":  "8.3500",
                                                   "5. volume":  "837618"
                                               },
                                "2026-05-11":  {
                                                   "1. open":  "8.5700",
                                                   "2. high":  "8.8900",
                                                   "3. low":  "8.5400",
                                                   "4. close":  "8.7300",
                                                   "5. volume":  "1084073"
                                               },
                                "2026-05-08":  {
                                                   "1. open":  "8.2900",
                                                   "2. high":  "8.6350",
                                                   "3. low":  "8.1650",
                                                   "4. close":  "8.6200",
                                                   "5. volume":  "766470"
                                               },
                                "2026-05-07":  {
                                                   "1. open":  "8.6000",
                                                   "2. high":  "8.6500",
                                                   "3. low":  "8.1700",
                                                   "4. close":  "8.3600",
                                                   "5. volume":  "1275984"
                                               },
                                "2026-05-06":  {
                                                   "1. open":  "9.0600",
                                                   "2. high":  "9.0600",
                                                   "3. low":  "8.6150",
                                                   "4. close":  "8.6900",
                                                   "5. volume":  "1661382"
                                               },
                                "2026-05-05":  {
                                                   "1. open":  "9.0500",
                                                   "2. high":  "9.3400",
                                                   "3. low":  "8.9500",
                                                   "4. close":  "8.9700",
                                                   "5. volume":  "1664848"
                                               },
                                "2026-05-04":  {
                                                   "1. open":  "9.0300",
                                                   "2. high":  "9.1700",
                                                   "3. low":  "8.8100",
                                                   "4. close":  "8.8800",
                                                   "5. volume":  "1171088"
                                               },
                                "2026-05-01":  {
                                                   "1. open":  "8.6000",
                                                   "2. high":  "9.0000",
                                                   "3. low":  "8.5500",
                                                   "4. close":  "8.9400",
                                                   "5. volume":  "1740975"
                                               },
                                "2026-04-30":  {
                                                   "1. open":  "7.9500",
                                                   "2. high":  "8.4600",
                                                   "3. low":  "7.8600",
                                                   "4. close":  "8.3400",
                                                   "5. volume":  "1770054"
                                               },
                                "2026-04-29":  {
                                                   "1. open":  "8.0100",
                                                   "2. high":  "8.0450",
                                                   "3. low":  "7.7363",
                                                   "4. close":  "7.8300",
                                                   "5. volume":  "1112513"
                                               },
                                "2026-04-28":  {
                                                   "1. open":  "7.7800",
                                                   "2. high":  "8.0000",
                                                   "3. low":  "7.6000",
                                                   "4. close":  "7.9700",
                                                   "5. volume":  "989063"
                                               },
                                "2026-04-27":  {
                                                   "1. open":  "7.8300",
                                                   "2. high":  "8.3000",
                                                   "3. low":  "7.8100",
                                                   "4. close":  "7.8900",
                                                   "5. volume":  "1249085"
                                               },
                                "2026-04-24":  {
                                                   "1. open":  "7.8400",
                                                   "2. high":  "7.9400",
                                                   "3. low":  "7.7400",
                                                   "4. close":  "7.8000",
                                                   "5. volume":  "562330"
                                               },
                                "2026-04-23":  {
                                                   "1. open":  "7.7500",
                                                   "2. high":  "8.0300",
                                                   "3. low":  "7.6000",
                                                   "4. close":  "7.8000",
                                                   "5. volume":  "727808"
                                               },
                                "2026-04-22":  {
                                                   "1. open":  "7.7600",
                                                   "2. high":  "8.1900",
                                                   "3. low":  "7.7196",
                                                   "4. close":  "7.8700",
                                                   "5. volume":  "1011005"
                                               },
                                "2026-04-21":  {
                                                   "1. open":  "7.9300",
                                                   "2. high":  "7.9300",
                                                   "3. low":  "7.5100",
                                                   "4. close":  "7.5200",
                                                   "5. volume":  "827306"
                                               },
                                "2026-04-20":  {
                                                   "1. open":  "7.9000",
                                                   "2. high":  "7.9397",
                                                   "3. low":  "7.6950",
                                                   "4. close":  "7.9200",
                                                   "5. volume":  "858010"
                                               },
                                "2026-04-17":  {
                                                   "1. open":  "7.8700",
                                                   "2. high":  "8.1650",
                                                   "3. low":  "7.7600",
                                                   "4. close":  "8.0200",
                                                   "5. volume":  "1649569"
                                               },
                                "2026-04-16":  {
                                                   "1. open":  "7.4750",
                                                   "2. high":  "7.6700",
                                                   "3. low":  "7.1650",
                                                   "4. close":  "7.6400",
                                                   "5. volume":  "1614519"
                                               },
                                "2026-04-15":  {
                                                   "1. open":  "7.4200",
                                                   "2. high":  "7.5200",
                                                   "3. low":  "7.3000",
                                                   "4. close":  "7.4000",
                                                   "5. volume":  "1614304"
                                               },
                                "2026-04-14":  {
                                                   "1. open":  "7.1300",
                                                   "2. high":  "7.4500",
                                                   "3. low":  "7.0985",
                                                   "4. close":  "7.3500",
                                                   "5. volume":  "1867152"
                                               },
                                "2026-04-13":  {
                                                   "1. open":  "6.6600",
                                                   "2. high":  "6.9800",
                                                   "3. low":  "6.5100",
                                                   "4. close":  "6.9800",
                                                   "5. volume":  "840025"
                                               },
                                "2026-04-10":  {
                                                   "1. open":  "6.8000",
                                                   "2. high":  "6.8700",
                                                   "3. low":  "6.6400",
                                                   "4. close":  "6.6700",
                                                   "5. volume":  "903132"
                                               },
                                "2026-04-09":  {
                                                   "1. open":  "6.3600",
                                                   "2. high":  "6.6500",
                                                   "3. low":  "6.3100",
                                                   "4. close":  "6.6400",
                                                   "5. volume":  "992696"
                                               },
                                "2026-04-08":  {
                                                   "1. open":  "6.5300",
                                                   "2. high":  "6.7800",
                                                   "3. low":  "6.3850",
                                                   "4. close":  "6.4000",
                                                   "5. volume":  "1289549"
                                               },
                                "2026-04-07":  {
                                                   "1. open":  "6.3000",
                                                   "2. high":  "6.4300",
                                                   "3. low":  "6.1700",
                                                   "4. close":  "6.1900",
                                                   "5. volume":  "1032266"
                                               },
                                "2026-04-06":  {
                                                   "1. open":  "6.2700",
                                                   "2. high":  "6.6364",
                                                   "3. low":  "6.2500",
                                                   "4. close":  "6.3900",
                                                   "5. volume":  "1325921"
                                               },
                                "2026-04-02":  {
                                                   "1. open":  "5.9300",
                                                   "2. high":  "6.2350",
                                                   "3. low":  "5.6200",
                                                   "4. close":  "6.1600",
                                                   "5. volume":  "967965"
                                               },
                                "2026-04-01":  {
                                                   "1. open":  "6.3000",
                                                   "2. high":  "6.4400",
                                                   "3. low":  "6.0700",
                                                   "4. close":  "6.0700",
                                                   "5. volume":  "1155665"
                                               },
                                "2026-03-31":  {
                                                   "1. open":  "6.3300",
                                                   "2. high":  "6.4100",
                                                   "3. low":  "6.0200",
                                                   "4. close":  "6.4000",
                                                   "5. volume":  "1700943"
                                               },
                                "2026-03-30":  {
                                                   "1. open":  "6.3800",
                                                   "2. high":  "6.5400",
                                                   "3. low":  "6.2100",
                                                   "4. close":  "6.2700",
                                                   "5. volume":  "1368109"
                                               },
                                "2026-03-27":  {
                                                   "1. open":  "6.4500",
                                                   "2. high":  "6.5000",
                                                   "3. low":  "6.1400",
                                                   "4. close":  "6.4100",
                                                   "5. volume":  "1622376"
                                               },
                                "2026-03-26":  {
                                                   "1. open":  "7.0400",
                                                   "2. high":  "7.1350",
                                                   "3. low":  "6.5200",
                                                   "4. close":  "6.5500",
                                                   "5. volume":  "1488112"
                                               },
                                "2026-03-25":  {
                                                   "1. open":  "7.0900",
                                                   "2. high":  "7.3499",
                                                   "3. low":  "7.0700",
                                                   "4. close":  "7.1700",
                                                   "5. volume":  "1201239"
                                               },
                                "2026-03-24":  {
                                                   "1. open":  "6.8800",
                                                   "2. high":  "7.1700",
                                                   "3. low":  "6.8800",
                                                   "4. close":  "7.0300",
                                                   "5. volume":  "1571416"
                                               },
                                "2026-03-23":  {
                                                   "1. open":  "7.0000",
                                                   "2. high":  "7.4500",
                                                   "3. low":  "6.6800",
                                                   "4. close":  "6.9600",
                                                   "5. volume":  "2356326"
                                               },
                                "2026-03-20":  {
                                                   "1. open":  "7.2700",
                                                   "2. high":  "7.2700",
                                                   "3. low":  "6.8939",
                                                   "4. close":  "7.1600",
                                                   "5. volume":  "22579465"
                                               },
                                "2026-03-19":  {
                                                   "1. open":  "6.8500",
                                                   "2. high":  "7.1800",
                                                   "3. low":  "6.7000",
                                                   "4. close":  "7.0700",
                                                   "5. volume":  "1365983"
                                               },
                                "2026-03-18":  {
                                                   "1. open":  "7.2500",
                                                   "2. high":  "7.2500",
                                                   "3. low":  "6.9400",
                                                   "4. close":  "7.0200",
                                                   "5. volume":  "1605545"
                                               },
                                "2026-03-17":  {
                                                   "1. open":  "7.2000",
                                                   "2. high":  "7.4000",
                                                   "3. low":  "7.0500",
                                                   "4. close":  "7.3500",
                                                   "5. volume":  "1618234"
                                               },
                                "2026-03-16":  {
                                                   "1. open":  "6.9800",
                                                   "2. high":  "7.3100",
                                                   "3. low":  "6.8700",
                                                   "4. close":  "7.2700",
                                                   "5. volume":  "1415987"
                                               },
                                "2026-03-13":  {
                                                   "1. open":  "7.0000",
                                                   "2. high":  "7.0900",
                                                   "3. low":  "6.8200",
                                                   "4. close":  "6.8200",
                                                   "5. volume":  "1067538"
                                               },
                                "2026-03-12":  {
                                                   "1. open":  "6.9500",
                                                   "2. high":  "7.0142",
                                                   "3. low":  "6.6800",
                                                   "4. close":  "6.7100",
                                                   "5. volume":  "1006081"
                                               },
                                "2026-03-11":  {
                                                   "1. open":  "6.9800",
                                                   "2. high":  "7.1400",
                                                   "3. low":  "6.8500",
                                                   "4. close":  "7.0400",
                                                   "5. volume":  "889527"
                                               },
                                "2026-03-10":  {
                                                   "1. open":  "6.8700",
                                                   "2. high":  "7.0800",
                                                   "3. low":  "6.8100",
                                                   "4. close":  "6.9300",
                                                   "5. volume":  "1228332"
                                               },
                                "2026-03-09":  {
                                                   "1. open":  "6.0600",
                                                   "2. high":  "6.8500",
                                                   "3. low":  "6.0600",
                                                   "4. close":  "6.7700",
                                                   "5. volume":  "1952873"
                                               },
                                "2026-03-06":  {
                                                   "1. open":  "6.3000",
                                                   "2. high":  "6.7010",
                                                   "3. low":  "6.1150",
                                                   "4. close":  "6.1200",
                                                   "5. volume":  "547003"
                                               },
                                "2026-03-05":  {
                                                   "1. open":  "6.6000",
                                                   "2. high":  "6.6650",
                                                   "3. low":  "6.3050",
                                                   "4. close":  "6.5900",
                                                   "5. volume":  "1081117"
                                               },
                                "2026-03-04":  {
                                                   "1. open":  "6.6000",
                                                   "2. high":  "6.8264",
                                                   "3. low":  "6.5900",
                                                   "4. close":  "6.6900",
                                                   "5. volume":  "915292"
                                               },
                                "2026-03-03":  {
                                                   "1. open":  "6.0000",
                                                   "2. high":  "6.3000",
                                                   "3. low":  "5.9200",
                                                   "4. close":  "6.1800",
                                                   "5. volume":  "527856"
                                               },
                                "2026-03-02":  {
                                                   "1. open":  "5.6800",
                                                   "2. high":  "6.2450",
                                                   "3. low":  "5.6100",
                                                   "4. close":  "6.2000",
                                                   "5. volume":  "881065"
                                               },
                                "2026-02-27":  {
                                                   "1. open":  "6.1000",
                                                   "2. high":  "6.2000",
                                                   "3. low":  "5.6600",
                                                   "4. close":  "5.7400",
                                                   "5. volume":  "851100"
                                               },
                                "2026-02-26":  {
                                                   "1. open":  "6.5200",
                                                   "2. high":  "6.5200",
                                                   "3. low":  "6.1550",
                                                   "4. close":  "6.2000",
                                                   "5. volume":  "540527"
                                               },
                                "2026-02-25":  {
                                                   "1. open":  "6.2900",
                                                   "2. high":  "6.6050",
                                                   "3. low":  "6.2100",
                                                   "4. close":  "6.5400",
                                                   "5. volume":  "1302599"
                                               },
                                "2026-02-24":  {
                                                   "1. open":  "5.9600",
                                                   "2. high":  "6.1300",
                                                   "3. low":  "5.9550",
                                                   "4. close":  "6.0400",
                                                   "5. volume":  "519692"
                                               },
                                "2026-02-23":  {
                                                   "1. open":  "6.2100",
                                                   "2. high":  "6.3572",
                                                   "3. low":  "5.9102",
                                                   "4. close":  "6.0200",
                                                   "5. volume":  "686467"
                                               },
                                "2026-02-20":  {
                                                   "1. open":  "6.2600",
                                                   "2. high":  "6.4400",
                                                   "3. low":  "6.1500",
                                                   "4. close":  "6.1500",
                                                   "5. volume":  "703581"
                                               },
                                "2026-02-19":  {
                                                   "1. open":  "6.3200",
                                                   "2. high":  "6.3200",
                                                   "3. low":  "6.0600",
                                                   "4. close":  "6.2700",
                                                   "5. volume":  "671840"
                                               },
                                "2026-02-18":  {
                                                   "1. open":  "6.4900",
                                                   "2. high":  "6.5300",
                                                   "3. low":  "6.1900",
                                                   "4. close":  "6.3100",
                                                   "5. volume":  "652866"
                                               },
                                "2026-02-17":  {
                                                   "1. open":  "6.4100",
                                                   "2. high":  "6.6400",
                                                   "3. low":  "6.0100",
                                                   "4. close":  "6.4200",
                                                   "5. volume":  "920659"
                                               },
                                "2026-02-13":  {
                                                   "1. open":  "5.9000",
                                                   "2. high":  "6.5100",
                                                   "3. low":  "5.9000",
                                                   "4. close":  "6.4000",
                                                   "5. volume":  "917372"
                                               },
                                "2026-02-12":  {
                                                   "1. open":  "6.1100",
                                                   "2. high":  "6.1700",
                                                   "3. low":  "5.7500",
                                                   "4. close":  "5.8000",
                                                   "5. volume":  "1077538"
                                               },
                                "2026-02-11":  {
                                                   "1. open":  "6.2300",
                                                   "2. high":  "6.3000",
                                                   "3. low":  "5.9150",
                                                   "4. close":  "6.0500",
                                                   "5. volume":  "906014"
                                               },
                                "2026-02-10":  {
                                                   "1. open":  "6.4000",
                                                   "2. high":  "6.4800",
                                                   "3. low":  "6.1200",
                                                   "4. close":  "6.2900",
                                                   "5. volume":  "865580"
                                               },
                                "2026-02-09":  {
                                                   "1. open":  "6.3800",
                                                   "2. high":  "6.6000",
                                                   "3. low":  "6.3100",
                                                   "4. close":  "6.4300",
                                                   "5. volume":  "784705"
                                               },
                                "2026-02-06":  {
                                                   "1. open":  "6.2200",
                                                   "2. high":  "6.6800",
                                                   "3. low":  "6.1601",
                                                   "4. close":  "6.5100",
                                                   "5. volume":  "1514594"
                                               },
                                "2026-02-05":  {
                                                   "1. open":  "6.4700",
                                                   "2. high":  "6.7407",
                                                   "3. low":  "5.8800",
                                                   "4. close":  "5.9200",
                                                   "5. volume":  "1448574"
                                               },
                                "2026-02-04":  {
                                                   "1. open":  "7.0300",
                                                   "2. high":  "7.0900",
                                                   "3. low":  "6.6200",
                                                   "4. close":  "6.7600",
                                                   "5. volume":  "1058716"
                                               },
                                "2026-02-03":  {
                                                   "1. open":  "7.4200",
                                                   "2. high":  "7.5100",
                                                   "3. low":  "6.7500",
                                                   "4. close":  "7.0600",
                                                   "5. volume":  "1162052"
                                               },
                                "2026-02-02":  {
                                                   "1. open":  "7.3900",
                                                   "2. high":  "7.6900",
                                                   "3. low":  "7.2770",
                                                   "4. close":  "7.5400",
                                                   "5. volume":  "1534909"
                                               },
                                "2026-01-30":  {
                                                   "1. open":  "7.4800",
                                                   "2. high":  "7.8500",
                                                   "3. low":  "7.4100",
                                                   "4. close":  "7.6000",
                                                   "5. volume":  "1029615"
                                               },
                                "2026-01-29":  {
                                                   "1. open":  "8.4100",
                                                   "2. high":  "8.4100",
                                                   "3. low":  "7.6000",
                                                   "4. close":  "7.6000",
                                                   "5. volume":  "1058844"
                                               },
                                "2026-01-28":  {
                                                   "1. open":  "8.5900",
                                                   "2. high":  "8.6000",
                                                   "3. low":  "8.2200",
                                                   "4. close":  "8.3300",
                                                   "5. volume":  "705440"
                                               }
                            }
}
